bokeh_catplot/__init__.py
bokeh_catplot/cat.py
bokeh_catplot/dist.py
bokeh_catplot/utils.py
bokeh_catplot-0.1.9.dist-info/LICENSE
bokeh_catplot-0.1.9.dist-info/METADATA
bokeh_catplot-0.1.9.dist-info/WHEEL
bokeh_catplot-0.1.9.dist-info/top_level.txt
bokeh_catplot-0.1.9.dist-info/RECORD
